<?xml version="1.0" encoding="UTF-8"?>
<moviemasher>

<!-- IMAGES -->
	<media group="image" type="image" id="beachimage" label="Beach" url="../media/image/Beach/media.jpg" fill="crop" />
	<media group="image" type="image" id="lightsimage" label="Lights" url="../media/image/Lights/media.jpg" fill="crop" />
	<media group="image" type="image" id="riversimage" label="Rivers" url="../media/image/Rivers/media.jpg" fill="crop" />
	<media group="image" type="image" id="cableimage" label="Cable" url="../media/image/Cable/media.jpg" fill="crop" />
	<media group="image" type="image" id="globeimage" label="Globe" url="../media/image/Globe/media.jpg" icon="../media/image/Globe/media.jpg" fill="scale" />
	<media group="image" type="image" id="frogimage" label="Frog" url="../media/image/Frog/media.jpg" fill="crop" />
	<media group="image" type="image" id="logoimage" label="Logo" url="../media/image/Logo/media.png" length='4' fill='scale' />
	<media group="image" type="image" id="starburstimage" label="Starburst" icon="../media/image/Starburst/media.png" url="../media/image/Starburst/media.png" />
</moviemasher>